{
  "db_name": "MySQL",
  "query": "SELECT cast(SUM(price * OrderDetails.quantity) as int) as result from OrderDetails INNER JOIN Stock ON OrderDetails.product_id = Stock.product_id WHERE order_id = ? ;",
  "describe": {
    "columns": [
      {
        "ordinal": 0,
        "name": "result",
        "type_info": {
          "type": "LongLong",
          "flags": "BINARY",
          "max_size": 20
        }
      }
    ],
    "parameters": {
      "Right": 1
    },
    "nullable": [
      true
    ]
  },
  "hash": "f84caa9276d8547a2d3c908b42f3171e8af15df51b7fc2f6bc3085ca582a25fc"
}
