{
  "db_name": "MySQL",
  "query": "SELECT email, role as \"role: Role\" FROM Users",
  "describe": {
    "columns": [
      {
        "ordinal": 0,
        "name": "email",
        "type_info": {
          "type": "VarString",
          "flags": "NOT_NULL | UNIQUE_KEY | NO_DEFAULT_VALUE",
          "max_size": 1020
        }
      },
      {
        "ordinal": 1,
        "name": "role: Role",
        "type_info": {
          "type": "String",
          "flags": "NOT_NULL | ENUM | NO_DEFAULT_VALUE",
          "max_size": 24
        }
      }
    ],
    "parameters": {
      "Right": 0
    },
    "nullable": [
      false,
      false
    ]
  },
  "hash": "7da3ec6649ad2ae5dd3b9b7ab812b05df3e0c7db9d1a793e3804bdec6fe4574a"
}
